{
    "id": "20230218_182650_63_2424",
    "type": "Feature",
    "geometry": {
        "type": "Polygon",
        "coordinates": [
            [
                [
                    -119.7355,
                    37.1098
                ],
                [
                    -119.7355,
                    37.1128
                ],
                [
                    -119.732,
                    37.1128
                ],
                [
                    -119.732,
                    37.1098
                ],
                [
                    -119.7355,
                    37.1098
                ]
            ]
        ]
    },
    "properties": {
        "acquired": "2023-02-18T18:26:50.633638Z",
        "anomalous_pixels": 0,
        "clear_confidence_percent": 98,
        "clear_percent": 100,
        "cloud_cover": 0.0,
        "cloud_percent": 0,
        "ground_control": true,
        "gsd": 3.9,
        "heavy_haze_percent": 0,
        "instrument": "PSB.SD",
        "item_type": "PSScene",
        "light_haze_percent": 0,
        "pixel_resolution": 3,
        "provider": "planetscope",
        "published": "2023-02-19T01:06:47Z",
        "publishing_stage": "finalized",
        "quality_category": "standard",
        "satellite_azimuth": 102.8,
        "satellite_id": "2424",
        "shadow_percent": 0,
        "snow_ice_percent": 0,
        "strip_id": "6297347",
        "sun_azimuth": 147.8,
        "sun_elevation": 35.7,
        "updated": "2023-03-09T18:29:41Z",
        "view_angle": 2.7,
        "visible_confidence_percent": 98,
        "visible_percent": 100
    }
}