{
    "id": "20230330_144433_77_2429",
    "type": "Feature",
    "geometry": {
        "type": "Polygon",
        "coordinates": [
            [
                [
                    -72.174,
                    42.5413
                ],
                [
                    -72.174,
                    42.5443
                ],
                [
                    -72.1703,
                    42.5443
                ],
                [
                    -72.1703,
                    42.5413
                ],
                [
                    -72.174,
                    42.5413
                ]
            ]
        ]
    },
    "properties": {
        "acquired": "2023-03-30T14:44:33.778636Z",
        "anomalous_pixels": 0,
        "clear_confidence_percent": 95,
        "clear_percent": 100,
        "cloud_cover": 0.0,
        "cloud_percent": 0,
        "ground_control": true,
        "gsd": 3.8,
        "heavy_haze_percent": 0,
        "instrument": "PSB.SD",
        "item_type": "PSScene",
        "light_haze_percent": 0,
        "pixel_resolution": 3,
        "provider": "planetscope",
        "published": "2023-03-31T02:24:04Z",
        "publishing_stage": "finalized",
        "quality_category": "standard",
        "satellite_azimuth": 278.1,
        "satellite_id": "2429",
        "shadow_percent": 0,
        "snow_ice_percent": 0,
        "strip_id": "6395548",
        "sun_azimuth": 133.8,
        "sun_elevation": 41.4,
        "updated": "2023-04-03T03:28:26Z",
        "view_angle": 5.1,
        "visible_confidence_percent": 95,
        "visible_percent": 100
    }
}