{
    "id": "20240515_185228_07_24bd",
    "type": "Feature",
    "geometry": {
        "type": "Polygon",
        "coordinates": [
            [
                [
                    -119.7355,
                    37.1098
                ],
                [
                    -119.7355,
                    37.1128
                ],
                [
                    -119.732,
                    37.1128
                ],
                [
                    -119.732,
                    37.1098
                ],
                [
                    -119.7355,
                    37.1098
                ]
            ]
        ]
    },
    "properties": {
        "acquired": "2024-05-15T18:52:28.071123Z",
        "anomalous_pixels": 0,
        "clear_confidence_percent": 94,
        "clear_percent": 100,
        "cloud_cover": 0.0,
        "cloud_percent": 0,
        "ground_control": true,
        "gsd": 3.9,
        "heavy_haze_percent": 0,
        "instrument": "PSB.SD",
        "item_type": "PSScene",
        "light_haze_percent": 0,
        "pixel_resolution": 3,
        "provider": "planetscope",
        "published": "2024-05-15T21:16:21Z",
        "publishing_stage": "finalized",
        "quality_category": "standard",
        "satellite_azimuth": 109.8,
        "satellite_id": "24bd",
        "shadow_percent": 0,
        "snow_ice_percent": 0,
        "strip_id": "7304997",
        "sun_azimuth": 138.5,
        "sun_elevation": 67.5,
        "updated": "2024-05-17T21:59:58Z",
        "view_angle": 0.9,
        "visible_confidence_percent": 94,
        "visible_percent": 100
    }
}